pycrafter4500/__init__.py
pycrafter4500/pycrafter4500.py
pycrafter4500-0.7.dist-info/LICENSE.txt
pycrafter4500-0.7.dist-info/METADATA
pycrafter4500-0.7.dist-info/WHEEL
pycrafter4500-0.7.dist-info/top_level.txt
pycrafter4500-0.7.dist-info/RECORD
