Metadata-Version: 2.1
Name: pycrafter4500
Version: 0.7
Summary: A python interface to communicate over USB with the TI Lightcrafter 4500
Home-page: https://pycrafter4500.readthedocs.io/en/latest/
Author: Alexander Tomlinson
Author-email: tomlinsa@ohsu.edu
License: GPL
Project-URL: Source Code, https://github.com/SivyerLab/pyCrafter4500
Keywords: lightcrafter 4500 dlpc 350 projector texas
Platform: UNKNOWN
License-File: LICENSE.txt
Requires-Dist: pyusb
